[
  {
    "廠商": "良級懸賞",
    "關鍵字IP": "鬼滅之刃",
    "編碼": "JBEW02250204165",
    "商品名稱": "逆刃 一戰封神 香奈乎 伊之助 vs 上弦二 童磨",
    "數量": "1",
    "成本": "15120",
    "點數價": "18144",
    "20洞價格": "2160",
    "40洞價格": "1130",
    "60洞價格": "753",
    "80洞價格": "565",
    "備註": "",
    "商品連結": "https://reurl.cc/O5KbkX"
  },
  {
    "廠商": "良級懸賞",
    "關鍵字IP": "鬼滅之刃",
    "編碼": "9VWD02250116439",
    "商品名稱": "逆刃 九柱共鳴第四彈 炎柱 煉獄杏壽郎 高配對戰版",
    "數量": "1",
    "成本": "7128",
    "點數價": "8553",
    "20洞價格": "1018",
    "40洞價格": "559",
    "60洞價格": "372",
    "80洞價格": "279",
    "備註": "",
    "商品連結": "https://reurl.cc/G5DQ5G"
  },
  {
    "廠商": "良級懸賞",
    "關鍵字IP": "鬼滅之刃",
    "編碼": "LXJU0224122236",
    "商品名稱": "魔方 珠世小姐 1:6",
    "數量": "1",
    "成本": "4860",
    "點數價": "5832",
    "20洞價格": "694",
    "40洞價格": "397",
    "60洞價格": "264",
    "80洞價格": "198",
    "備註": "",
    "商品連結": "https://reurl.cc/geGVAN"
  },
  {
    "廠商": "良級懸賞",
    "關鍵字IP": "鬼滅之刃",
    "編碼": "94ZY02250212115",
    "商品名稱": "TY天元 捆綁彌豆子 SM小姐姐系列 1:6",
    "數量": "1",
    "成本": "7020",
    "點數價": "8424",
    "20洞價格": "1002",
    "40洞價格": "551",
    "60洞價格": "367",
    "80洞價格": "275",
    "備註": "",
    "商品連結": "https://reurl.cc/RL30XG"
  },
  {
    "廠商": "良級懸賞",
    "關鍵字IP": "鬼滅之刃",
    "編碼": "09I20124122653",
    "商品名稱": "FIT 禰豆子 血鬼術爆血 1:6",
    "數量": "1",
    "成本": "6632",
    "點數價": "7958",
    "20洞價格": "947",
    "40洞價格": "523",
    "60洞價格": "349",
    "80洞價格": "261",
    "備註": "",
    "商品連結": "https://reurl.cc/qnnyag"
  },
  {
    "廠商": "良級懸賞",
    "關鍵字IP": "鬼滅之刃",
    "編碼": "GDSC1-1001",
    "商品名稱": "CP 炎柱 煉獄杏壽郎",
    "數量": "1",
    "成本": "1000",
    "點數價": "1200",
    "20洞價格": "142",
    "40洞價格": "121",
    "60洞價格": "80",
    "80洞價格": "60",
    "備註": "",
    "商品連結": "https://tinyurl.com/2a5826m6"
  },
  {
    "廠商": "良級懸賞",
    "關鍵字IP": "間諜家家酒",
    "編碼": "5Y780125033057",
    "商品名稱": "整活 無臉男安妮亞 壞笑版",
    "數量": "2",
    "成本": "1865",
    "點數價": "2238",
    "20洞價格": "266",
    "40洞價格": "183",
    "60洞價格": "122",
    "80洞價格": "91",
    "備註": "",
    "商品連結": "https://reurl.cc/nmOd3X"
  },
  {
    "廠商": "良級懸賞",
    "關鍵字IP": "間諜家家酒",
    "編碼": "POXN0325020621",
    "商品名稱": "WAKU 黃裙安妮亞 留聲機粉紅女孩",
    "數量": "1",
    "成本": "2200",
    "點數價": "2658",
    "20洞價格": "316",
    "40洞價格": "208",
    "60洞價格": "138",
    "80洞價格": "104",
    "備註": "",
    "商品連結": "https://reurl.cc/xpVDE4"
  },
  {
    "廠商": "良級懸賞",
    "關鍵字IP": "鬼滅之刃",
    "編碼": "JBEW02250204165",
    "商品名稱": "逆刃 一戰封神 香奈乎 伊之助 vs 上弦二 童磨",
    "數量": "1",
    "成本": "15120",
    "點數價": "18144",
    "20洞價格": "2160",
    "40洞價格": "1130",
    "60洞價格": "753",
    "80洞價格": "565",
    "備註": "",
    "商品連結": "https://reurl.cc/O5KbkX"
  },
  {
    "廠商": "良級懸賞",
    "關鍵字IP": "鬼滅之刃",
    "編碼": "9VWD02250116439",
    "商品名稱": "逆刃 九柱共鳴第四彈 炎柱 煉獄杏壽郎 高配對戰版",
    "數量": "1",
    "成本": "7128",
    "點數價": "8553",
    "20洞價格": "1018",
    "40洞價格": "559",
    "60洞價格": "372",
    "80洞價格": "279",
    "備註": "",
    "商品連結": "https://reurl.cc/G5DQ5G"
  },
  {
    "廠商": "良級懸賞",
    "關鍵字IP": "鬼滅之刃",
    "編碼": "LXJU0224122236",
    "商品名稱": "魔方 珠世小姐 1:6",
    "數量": "1",
    "成本": "4860",
    "點數價": "5832",
    "20洞價格": "694",
    "40洞價格": "397",
    "60洞價格": "264",
    "80洞價格": "198",
    "備註": "",
    "商品連結": "https://reurl.cc/geGVAN"
  },
  {
    "廠商": "良級懸賞",
    "關鍵字IP": "鬼滅之刃",
    "編碼": "94ZY02250212115",
    "商品名稱": "TY天元 捆綁彌豆子 SM小姐姐系列 1:6",
    "數量": "1",
    "成本": "7020",
    "點數價": "8424",
    "20洞價格": "1002",
    "40洞價格": "551",
    "60洞價格": "367",
    "80洞價格": "275",
    "備註": "",
    "商品連結": "https://reurl.cc/RL30XG"
  },
  {
    "廠商": "良級懸賞",
    "關鍵字IP": "鬼滅之刃",
    "編碼": "09I20124122653",
    "商品名稱": "FIT 禰豆子 血鬼術爆血 1:6",
    "數量": "1",
    "成本": "6632",
    "點數價": "7958",
    "20洞價格": "947",
    "40洞價格": "523",
    "60洞價格": "349",
    "80洞價格": "261",
    "備註": "",
    "商品連結": "https://reurl.cc/qnnyag"
  },
  {
    "廠商": "良級懸賞",
    "關鍵字IP": "鬼滅之刃",
    "編碼": "GDSC1-1001",
    "商品名稱": "CP 炎柱 煉獄杏壽郎",
    "數量": "1",
    "成本": "1000",
    "點數價": "1200",
    "20洞價格": "142",
    "40洞價格": "121",
    "60洞價格": "80",
    "80洞價格": "60",
    "備註": "",
    "商品連結": "https://tinyurl.com/2a5826m6"
  },
  {
    "廠商": "良級懸賞",
    "關鍵字IP": "間諜家家酒",
    "編碼": "5Y780125033057",
    "商品名稱": "整活 無臉男安妮亞 壞笑版",
    "數量": "2",
    "成本": "1865",
    "點數價": "2238",
    "20洞價格": "266",
    "40洞價格": "183",
    "60洞價格": "122",
    "80洞價格": "91",
    "備註": "",
    "商品連結": "https://reurl.cc/nmOd3X"
  },
  {
    "廠商": "良級懸賞",
    "關鍵字IP": "間諜家家酒",
    "編碼": "POXN0325020621",
    "商品名稱": "WAKU 黃裙安妮亞 留聲機粉紅女孩",
    "數量": "1",
    "成本": "2215",
    "點數價": "2658",
    "20洞價格": "316",
    "40洞價格": "208",
    "60洞價格": "138",
    "80洞價格": "104",
    "備註": "",
    "商品連結": "https://reurl.cc/xpVDE4"
  }
]